{"sm": {"sm": "LHEReweightingWeight[0]"}, "cW": {"sm_lin_quad_cW": "LHEReweightingWeight[1]", "quad_cW": "0.5*(LHEReweightingWeight[1]+LHEReweightingWeight[9]-2*LHEReweightingWeight[0])"}, "cW_cHDD": {"sm_lin_quad_mixed_cW_cHDD": "LHEReweightingWeight[17]"}, "cW_cHWB": {"sm_lin_quad_mixed_cW_cHWB": "LHEReweightingWeight[18]"}, "cW_cHl1": {"sm_lin_quad_mixed_cW_cHl1": "LHEReweightingWeight[19]"}, "cW_cHl3": {"sm_lin_quad_mixed_cW_cHl3": "LHEReweightingWeight[20]"}, "cW_cHq1": {"sm_lin_quad_mixed_cW_cHq1": "LHEReweightingWeight[21]"}, "cW_cHq3": {"sm_lin_quad_mixed_cW_cHq3": "LHEReweightingWeight[22]"}, "cW_cll1": {"sm_lin_quad_mixed_cW_cll1": "LHEReweightingWeight[23]"}, "cHDD": {"sm_lin_quad_cHDD": "LHEReweightingWeight[2]", "quad_cHDD": "0.5*(LHEReweightingWeight[2]+LHEReweightingWeight[10]-2*LHEReweightingWeight[0])"}, "cHDD_cHWB": {"sm_lin_quad_mixed_cHDD_cHWB": "LHEReweightingWeight[24]"}, "cHDD_cHl1": {"sm_lin_quad_mixed_cHDD_cHl1": "LHEReweightingWeight[25]"}, "cHDD_cHl3": {"sm_lin_quad_mixed_cHDD_cHl3": "LHEReweightingWeight[26]"}, "cHDD_cHq1": {"sm_lin_quad_mixed_cHDD_cHq1": "LHEReweightingWeight[27]"}, "cHDD_cHq3": {"sm_lin_quad_mixed_cHDD_cHq3": "LHEReweightingWeight[28]"}, "cHDD_cll1": {"sm_lin_quad_mixed_cHDD_cll1": "LHEReweightingWeight[29]"}, "cHWB": {"sm_lin_quad_cHWB": "LHEReweightingWeight[3]", "quad_cHWB": "0.5*(LHEReweightingWeight[3]+LHEReweightingWeight[11]-2*LHEReweightingWeight[0])"}, "cHWB_cHl1": {"sm_lin_quad_mixed_cHWB_cHl1": "LHEReweightingWeight[30]"}, "cHWB_cHl3": {"sm_lin_quad_mixed_cHWB_cHl3": "LHEReweightingWeight[31]"}, "cHWB_cHq1": {"sm_lin_quad_mixed_cHWB_cHq1": "LHEReweightingWeight[32]"}, "cHWB_cHq3": {"sm_lin_quad_mixed_cHWB_cHq3": "LHEReweightingWeight[33]"}, "cHWB_cll1": {"sm_lin_quad_mixed_cHWB_cll1": "LHEReweightingWeight[34]"}, "cHl1": {"sm_lin_quad_cHl1": "LHEReweightingWeight[4]", "quad_cHl1": "0.5*(LHEReweightingWeight[4]+LHEReweightingWeight[12]-2*LHEReweightingWeight[0])"}, "cHl1_cHl3": {"sm_lin_quad_mixed_cHl1_cHl3": "LHEReweightingWeight[35]"}, "cHl1_cHq1": {"sm_lin_quad_mixed_cHl1_cHq1": "LHEReweightingWeight[36]"}, "cHl1_cHq3": {"sm_lin_quad_mixed_cHl1_cHq3": "LHEReweightingWeight[37]"}, "cHl1_cll1": {"sm_lin_quad_mixed_cHl1_cll1": "LHEReweightingWeight[38]"}, "cHl3": {"sm_lin_quad_cHl3": "LHEReweightingWeight[5]", "quad_cHl3": "0.5*(LHEReweightingWeight[5]+LHEReweightingWeight[13]-2*LHEReweightingWeight[0])"}, "cHl3_cHq1": {"sm_lin_quad_mixed_cHl3_cHq1": "LHEReweightingWeight[39]"}, "cHl3_cHq3": {"sm_lin_quad_mixed_cHl3_cHq3": "LHEReweightingWeight[40]"}, "cHl3_cll1": {"sm_lin_quad_mixed_cHl3_cll1": "LHEReweightingWeight[41]"}, "cHq1": {"sm_lin_quad_cHq1": "LHEReweightingWeight[6]", "quad_cHq1": "0.5*(LHEReweightingWeight[6]+LHEReweightingWeight[14]-2*LHEReweightingWeight[0])"}, "cHq1_cHq3": {"sm_lin_quad_mixed_cHq1_cHq3": "LHEReweightingWeight[42]"}, "cHq1_cll1": {"sm_lin_quad_mixed_cHq1_cll1": "LHEReweightingWeight[43]"}, "cHq3": {"sm_lin_quad_cHq3": "LHEReweightingWeight[7]", "quad_cHq3": "0.5*(LHEReweightingWeight[7]+LHEReweightingWeight[15]-2*LHEReweightingWeight[0])"}, "cHq3_cll1": {"sm_lin_quad_mixed_cHq3_cll1": "LHEReweightingWeight[44]"}, "cll1": {"sm_lin_quad_cll1": "LHEReweightingWeight[8]", "quad_cll1": "0.5*(LHEReweightingWeight[8]+LHEReweightingWeight[16]-2*LHEReweightingWeight[0])"}}